README.txt
setup.cfg
setup.py
collective/__init__.py
collective.latin1Splitter.egg-info/PKG-INFO
collective.latin1Splitter.egg-info/SOURCES.txt
collective.latin1Splitter.egg-info/dependency_links.txt
collective.latin1Splitter.egg-info/entry_points.txt
collective.latin1Splitter.egg-info/namespace_packages.txt
collective.latin1Splitter.egg-info/not-zip-safe
collective.latin1Splitter.egg-info/paster_plugins.txt
collective.latin1Splitter.egg-info/requires.txt
collective.latin1Splitter.egg-info/top_level.txt
collective/latin1Splitter/__init__.py
collective/latin1Splitter/configure.zcml
collective/latin1Splitter/latin1_splitter.py
collective/latin1Splitter/setuphandlers.py
collective/latin1Splitter/profiles/default/collective.latin1Splitter_importVarious.txt
collective/latin1Splitter/profiles/default/import_steps.xml
docs/HISTORY.txt
docs/INSTALL.txt
docs/LICENSE.GPL
docs/LICENSE.txt