Metadata-Version: 1.0
Name: collective.latin1Splitter
Version: 1.1
Summary: UNKNOWN
Home-page: http://svn.plone.org/svn/plone/plone.example
Author: Quadra-Informatique
Author-email: plone-developers@lists.sourceforge.net
License: GPL
Platform: UNKNOWN
Classifier: Framework :: Plone
Classifier: Programming Language :: Python
Classifier: Topic :: Software Development :: Libraries :: Python Modules
